resource_wizard/__init__.py
resource_wizard/cookiecutter-resource/.gitignore
resource_wizard/cookiecutter-resource/cookiecutter.json
resource_wizard/cookiecutter-resource/{{cookiecutter.resource_kebap}}/{{cookiecutter.resource_kebap}}.abilities.ts
resource_wizard/cookiecutter-resource/{{cookiecutter.resource_kebap}}/{{cookiecutter.resource_kebap}}.controller.spec.ts
resource_wizard/cookiecutter-resource/{{cookiecutter.resource_kebap}}/{{cookiecutter.resource_kebap}}.controller.ts
resource_wizard/cookiecutter-resource/{{cookiecutter.resource_kebap}}/{{cookiecutter.resource_kebap}}.module.ts
resource_wizard/cookiecutter-resource/{{cookiecutter.resource_kebap}}/{{cookiecutter.resource_kebap}}.service.spec.ts
resource_wizard/cookiecutter-resource/{{cookiecutter.resource_kebap}}/{{cookiecutter.resource_kebap}}.service.ts
resource_wizard/cookiecutter-resource/{{cookiecutter.resource_kebap}}/entities/{{cookiecutter.resource_kebap}}.entity.ts
gg_resource_wizard-1.1.1.dist-info/entry_points.txt
gg_resource_wizard-1.1.1.dist-info/LICENSE
gg_resource_wizard-1.1.1.dist-info/WHEEL
gg_resource_wizard-1.1.1.dist-info/METADATA
gg_resource_wizard-1.1.1.dist-info/RECORD
