Metadata-Version: 2.1
Name: gg-resource-wizard
Version: 1.1.1
Summary: Create resource modules for gg-core.
Author-email: Robin De Schepper <robin.deschepper93@gmail.com>
Requires-Dist: click~=8.0
Requires-Dist: cookiecutter~=2.0
Project-URL: Home, https://github.com/AlvastBedankt/resource-wizard
